KLCserial/__init__.py
KLCserial/core.py
klcserial-0.23.dist-info/LICENSE
klcserial-0.23.dist-info/METADATA
klcserial-0.23.dist-info/WHEEL
klcserial-0.23.dist-info/top_level.txt
klcserial-0.23.dist-info/RECORD
