Metadata-Version: 2.2
Name: KLCserial
Version: 0.23
Summary: Functions and examples to control Thorlabs KLC controllers (KLC101) through serial commands with Python
Author-email: iancynk <ian.cynk@posteo.eu>
Project-URL: Homepage, https://github.com/iancynk/KLCserial
Project-URL: Bug Tracker, https://github.com/iancynk/KLCserial/issues
Classifier: Programming Language :: Python :: 3
Classifier: License :: OSI Approved :: MIT License
Classifier: Operating System :: POSIX :: Linux
Classifier: Intended Audience :: Education
Classifier: Intended Audience :: Science/Research
Classifier: Topic :: Scientific/Engineering
Classifier: Topic :: Scientific/Engineering :: Physics
Classifier: Topic :: Software Development :: Libraries
Classifier: Topic :: Software Development :: Libraries :: Python Modules
Requires-Python: >=3.10
License-File: LICENSE
